{
  "updatedAt": "2026-07-17T02:40:17.719303Z",
  "marketData": {
    "regional": {
      "nifty": {
        "current": 24072.75,
        "history_30d": [
          23416.55,
          23366.7,
          23123.0,
          23242.1,
          23214.95,
          23161.6,
          23622.9,
          23853.9,
          23989.15,
          24085.7,
          24168.0,
          24013.1,
          24102.9,
          23824.1,
          24021.65,
          24056.0,
          23946.25,
          23865.75,
          24005.85,
          24175.7,
          24270.85,
          24430.35,
          24398.7,
          23882.05,
          23962.8,
          24206.9,
          24211.0,
          24052.05,
          24078.5,
          24072.75
        ],
        "delta_1d": -0.02,
        "delta_1w": 0.46,
        "delta_1m": 0.35,
        "delta_3m": -0.51,
        "delta_6m": -6.97,
        "delta_1y": -4.52,
        "signal": "Buy",
        "rsi": 52.15,
        "macd": {
          "macd": 85.91,
          "signal": 103.01,
          "hist": -17.09
        },
        "pattern": {
          "pattern": "Consolidation",
          "target": 24554.21,
          "stop_loss": 22869.11,
          "strength": "Neutral"
        },
        "forecast_7d": [
          24374.74,
          24405.75,
          24436.76,
          24467.77,
          24498.78,
          24529.79,
          24560.81
        ]
      },
      "sensex": {
        "current": 77186.87,
        "history_30d": [
          74360.01,
          74243.34,
          73524.26,
          73918.76,
          73983.18,
          73832.55,
          75527.95,
          76264.33,
          76808.48,
          77155.62,
          77409.98,
          76802.9,
          77094.07,
          76200.68,
          76991.22,
          77100.47,
          76728.37,
          76478.67,
          76922.64,
          77502.12,
          77763.91,
          78285.07,
          78180.72,
          76503.6,
          76741.82,
          77569.39,
          77616.4,
          77054.94,
          77185.43,
          77186.87
        ],
        "delta_1d": 0.0,
        "delta_1w": 0.58,
        "delta_1m": 0.49,
        "delta_3m": -1.03,
        "delta_6m": -8.31,
        "delta_1y": -6.59,
        "signal": "Buy",
        "rsi": 53.15,
        "macd": {
          "macd": 346.01,
          "signal": 405.26,
          "hist": -59.25
        },
        "pattern": {
          "pattern": "Consolidation",
          "target": 78730.61,
          "stop_loss": 73327.53,
          "strength": "Neutral"
        },
        "forecast_7d": [
          78282.35,
          78401.77,
          78521.2,
          78640.62,
          78760.05,
          78879.47,
          78998.9
        ]
      },
      "vix": {
        "current": 12.88,
        "history_30d": [
          15.89,
          15.79,
          17.03,
          15.58,
          15.63,
          15.61,
          14.72,
          14.35,
          13.36,
          13.19,
          12.67,
          12.97,
          12.84,
          13.94,
          13.39,
          13.05,
          13.61,
          13.6,
          13.24,
          12.29,
          11.8,
          11.82,
          11.65,
          14.68,
          13.36,
          12.25,
          13.28,
          13.75,
          13.27,
          12.88
        ],
        "delta_1d": -2.94,
        "delta_1w": -3.59,
        "delta_1m": -3.59,
        "delta_3m": -28.8,
        "delta_6m": 21.51,
        "delta_1y": 14.59,
        "signal": "Sell",
        "rsi": 45.36,
        "macd": {
          "macd": -0.57,
          "signal": -0.77,
          "hist": 0.21
        },
        "pattern": {
          "pattern": "Consolidation",
          "target": 13.14,
          "stop_loss": 12.24,
          "strength": "Neutral"
        },
        "forecast_7d": [
          12.06,
          11.96,
          11.85,
          11.74,
          11.64,
          11.53,
          11.42
        ]
      }
    },
    "global": {
      "dji": {
        "current": 52552.97,
        "history_30d": [
          50687.07,
          51561.93,
          50866.78,
          50786.01,
          50872.11,
          49918.78,
          50848.75,
          51202.26,
          51671.03,
          51999.67,
          51492.55,
          51564.7,
          51712.71,
          51666.84,
          51848.9,
          51920.62,
          51876.11,
          52182.74,
          52319.2,
          52305.24,
          52900.07,
          53055.91,
          52925.15,
          52348.39,
          52487.41,
          52637.01,
          52498.64,
          52508.27,
          52658.64,
          52552.97
        ],
        "delta_1d": -0.2,
        "delta_1w": 0.12,
        "delta_1m": 1.71,
        "delta_3m": 8.18,
        "delta_6m": 6.92,
        "delta_1y": 18.14,
        "signal": "Buy",
        "rsi": 59.63,
        "macd": {
          "macd": 442.59,
          "signal": 506.02,
          "hist": -63.44
        },
        "pattern": {
          "pattern": "Consolidation",
          "target": 53604.03,
          "stop_loss": 49925.32,
          "strength": "Neutral"
        },
        "forecast_7d": [
          53051.88,
          53128.62,
          53205.35,
          53282.08,
          53358.81,
          53435.54,
          53512.27
        ]
      },
      "nasdaq": {
        "current": 25881.95,
        "history_30d": [
          26853.98,
          26830.96,
          25709.43,
          25929.66,
          25678.82,
          25169.5,
          25809.66,
          25888.84,
          26683.94,
          26376.34,
          26021.66,
          26517.93,
          26166.6,
          25587.04,
          25476.64,
          25358.6,
          25297.62,
          25820.14,
          26213.72,
          26040.03,
          25832.67,
          26121.16,
          25818.69,
          25870.65,
          26206.89,
          26281.61,
          25873.18,
          26107.01,
          26269.23,
          25881.95
        ],
        "delta_1d": -1.47,
        "delta_1w": -1.24,
        "delta_1m": -3.01,
        "delta_3m": 7.38,
        "delta_6m": 10.27,
        "delta_1y": 23.92,
        "signal": "Sell",
        "rsi": 48.65,
        "macd": {
          "macd": 33.26,
          "signal": 24.51,
          "hist": 8.75
        },
        "pattern": {
          "pattern": "Consolidation",
          "target": 26399.59,
          "stop_loss": 24587.85,
          "strength": "Neutral"
        },
        "forecast_7d": [
          25919.66,
          25915.14,
          25910.61,
          25906.09,
          25901.56,
          25897.04,
          25892.51
        ]
      },
      "nikkei": {
        "current": 63994.67,
        "history_30d": [
          64024.6,
          65416.63,
          64179.27,
          64217.27,
          66020.04,
          69317.5,
          69404.5,
          69902.25,
          71053.49,
          71250.06,
          72353.96,
          69788.38,
          69174.97,
          72366.34,
          69360.88,
          69468.11,
          70062.32,
          70474.96,
          68733.15,
          69744.07,
          69737.69,
          68256.96,
          66819.05,
          67743.85,
          68557.73,
          67242.73,
          67743.5,
          68751.51,
          66835.54,
          63994.67
        ],
        "delta_1d": -4.25,
        "delta_1w": -6.66,
        "delta_1m": -9.93,
        "delta_3m": 7.52,
        "delta_6m": 17.76,
        "delta_1y": 60.38,
        "signal": "Strong Sell",
        "rsi": 38.75,
        "macd": {
          "macd": -158.86,
          "signal": 489.66,
          "hist": -648.52
        },
        "pattern": {
          "pattern": "Consolidation",
          "target": 65274.56,
          "stop_loss": 60794.94,
          "strength": "Neutral"
        },
        "forecast_7d": [
          68694.49,
          68713.5,
          68732.51,
          68751.52,
          68770.53,
          68789.54,
          68808.54
        ]
      },
      "hangseng": {
        "current": 24691.89,
        "history_30d": [
          25253.4,
          24961.95,
          24657.06,
          24565.9,
          24407.96,
          24249.29,
          24718.1,
          24842.67,
          24493.95,
          24312.16,
          23924.81,
          23768.52,
          23336.28,
          23412.18,
          23076.91,
          22671.86,
          23026.68,
          22881.02,
          23055.03,
          23350.03,
          23616.32,
          23496.89,
          24199.46,
          24030.18,
          24175.12,
          24213.72,
          24340.73,
          24681.1,
          25008.6,
          24691.89
        ],
        "delta_1d": -1.27,
        "delta_1w": 2.14,
        "delta_1m": 0.81,
        "delta_3m": -6.45,
        "delta_6m": -5.87,
        "delta_1y": 0.79,
        "signal": "Strong Buy",
        "rsi": 56.76,
        "macd": {
          "macd": 25.18,
          "signal": -203.11,
          "hist": 228.29
        },
        "pattern": {
          "pattern": "Consolidation",
          "target": 25185.73,
          "stop_loss": 23457.3,
          "strength": "Neutral"
        },
        "forecast_7d": [
          23767.83,
          23749.8,
          23731.76,
          23713.73,
          23695.7,
          23677.67,
          23659.63
        ]
      },
      "ftse": {
        "current": 10572.2,
        "history_30d": [
          10368.1,
          10373.2,
          10227.3,
          10254.8,
          10303.9,
          10471.7,
          10430.6,
          10494.2,
          10508.6,
          10399.7,
          10363.3,
          10437.9,
          10428.9,
          10461.6,
          10529.9,
          10508.0,
          10484.2,
          10497.1,
          10478.3,
          10652.9,
          10679.0,
          10651.8,
          10665.9,
          10489.0,
          10472.5,
          10497.3,
          10498.3,
          10529.4,
          10515.9,
          10572.2
        ],
        "delta_1d": 0.54,
        "delta_1w": 0.95,
        "delta_1m": 0.61,
        "delta_3m": -0.89,
        "delta_6m": 3.29,
        "delta_1y": 18.43,
        "signal": "Strong Buy",
        "rsi": 56.06,
        "macd": {
          "macd": 30.93,
          "signal": 37.55,
          "hist": -6.62
        },
        "pattern": {
          "pattern": "Cup & Handle",
          "target": 11629.42,
          "stop_loss": 9972.43,
          "strength": "Bullish"
        },
        "forecast_7d": [
          10608.57,
          10617.2,
          10625.83,
          10634.45,
          10643.08,
          10651.71,
          10660.34
        ]
      }
    },
    "crypto": {
      "btc": {
        "current": 63354.0,
        "history_30d": [
          64418.45,
          62896.47,
          63540.84,
          64239.68,
          63237.54,
          63952.11,
          62668.02,
          60995.13,
          59721.68,
          60016.43,
          59940.1,
          59532.34,
          60138.38,
          58558.86,
          60003.76,
          61485.3,
          62544.2,
          63088.3,
          63547.88,
          63995.02,
          63297.39,
          62257.57,
          63193.15,
          64127.14,
          63802.03,
          63758.22,
          62239.12,
          64956.11,
          64712.38,
          63354.0
        ],
        "delta_1d": -2.1,
        "delta_1w": -0.7,
        "delta_1m": 6.08,
        "delta_3m": -19.87,
        "delta_6m": -10.73,
        "delta_1y": -46.89,
        "signal": "Buy",
        "rsi": 49.67,
        "macd": {
          "macd": 34.33,
          "signal": -337.65,
          "hist": 371.98
        },
        "pattern": {
          "pattern": "Consolidation",
          "target": 64621.08,
          "stop_loss": 60186.3,
          "strength": "Neutral"
        },
        "forecast_7d": [
          63285.07,
          63337.41,
          63389.74,
          63442.07,
          63494.4,
          63546.74,
          63599.07
        ]
      },
      "eth": {
        "current": 1842.94,
        "history_30d": [
          1747.89,
          1709.53,
          1710.98,
          1739.3,
          1704.58,
          1726.51,
          1665.44,
          1619.92,
          1564.82,
          1576.62,
          1571.59,
          1570.36,
          1610.21,
          1569.58,
          1608.96,
          1698.17,
          1756.52,
          1779.03,
          1783.01,
          1797.57,
          1768.51,
          1742.68,
          1744.48,
          1795.69,
          1788.1,
          1805.79,
          1773.5,
          1889.48,
          1916.94,
          1842.94
        ],
        "delta_1d": -3.86,
        "delta_1w": 3.07,
        "delta_1m": 17.77,
        "delta_3m": -17.11,
        "delta_6m": -11.93,
        "delta_1y": -46.99,
        "signal": "Strong Buy",
        "rsi": 57.29,
        "macd": {
          "macd": 34.32,
          "signal": 13.59,
          "hist": 20.73
        },
        "pattern": {
          "pattern": "Consolidation",
          "target": 1879.8,
          "stop_loss": 1750.79,
          "strength": "Neutral"
        },
        "forecast_7d": [
          1824.2,
          1830.97,
          1837.73,
          1844.5,
          1851.27,
          1858.04,
          1864.81
        ]
      },
      "sol": {
        "current": 74.76,
        "history_30d": [
          71.93,
          69.63,
          69.72,
          73.17,
          72.42,
          71.91,
          69.64,
          67.98,
          67.57,
          71.84,
          70.41,
          71.31,
          74.95,
          73.52,
          77.38,
          80.64,
          82.28,
          81.65,
          81.42,
          81.92,
          80.65,
          77.79,
          78.05,
          78.07,
          76.82,
          76.87,
          74.86,
          77.76,
          77.26,
          74.76
        ],
        "delta_1d": -3.24,
        "delta_1w": -2.68,
        "delta_1m": 10.64,
        "delta_3m": -16.19,
        "delta_6m": -15.19,
        "delta_1y": -57.47,
        "signal": "Sell",
        "rsi": 46.3,
        "macd": {
          "macd": 0.64,
          "signal": 1.1,
          "hist": -0.46
        },
        "pattern": {
          "pattern": "Bull Flag",
          "target": 80.74,
          "stop_loss": 66.22,
          "strength": "Strong Bullish"
        },
        "forecast_7d": [
          80.23,
          80.56,
          80.89,
          81.21,
          81.54,
          81.87,
          82.2
        ]
      }
    },
    "sectors": {
      "IT": {
        "current": 28722.6,
        "history_30d": [
          29300.6,
          29010.3,
          28653.55,
          28516.25,
          28279.95,
          27821.05,
          27795.75,
          28067.9,
          28568.1,
          28809.55,
          28466.45,
          27426.85,
          27628.55,
          27012.05,
          27566.7,
          27330.85,
          27038.5,
          26299.05,
          25769.8,
          26965.05,
          27439.4,
          27276.45,
          27939.15,
          27555.2,
          27471.25,
          28010.4,
          29015.85,
          28724.75,
          28532.25,
          28722.6
        ],
        "delta_1d": 0.67,
        "delta_1w": 4.56,
        "delta_1m": 0.54,
        "delta_3m": -9.73,
        "delta_6m": -24.26,
        "delta_1y": -23.73,
        "signal": "Strong Buy",
        "rsi": 55.85,
        "macd": {
          "macd": 56.48,
          "signal": -189.83,
          "hist": 246.32
        },
        "pattern": {
          "pattern": "Consolidation",
          "target": 29297.05,
          "stop_loss": 27286.47,
          "strength": "Neutral"
        },
        "forecast_7d": [
          27560.8,
          27538.89,
          27516.97,
          27495.06,
          27473.14,
          27451.23,
          27429.31
        ]
      },
      "Pharma": {
        "current": 26008.05,
        "history_30d": [
          24177.95,
          24248.05,
          24147.65,
          24290.3,
          24160.75,
          24306.95,
          24380.05,
          24220.1,
          24157.85,
          24146.55,
          24282.2,
          24460.3,
          24762.9,
          24989.95,
          25018.95,
          24969.5,
          25227.9,
          25326.4,
          25182.7,
          25308.9,
          25745.15,
          25866.25,
          25677.7,
          25429.8,
          25656.25,
          25674.1,
          25643.35,
          25907.1,
          26003.6,
          26008.05
        ],
        "delta_1d": 0.02,
        "delta_1w": 1.37,
        "delta_1m": 7.66,
        "delta_3m": 15.77,
        "delta_6m": 13.26,
        "delta_1y": 15.11,
        "signal": "Strong Buy",
        "rsi": 71.22,
        "macd": {
          "macd": 403.64,
          "signal": 375.75,
          "hist": 27.88
        },
        "pattern": {
          "pattern": "Consolidation",
          "target": 26528.21,
          "stop_loss": 24707.65,
          "strength": "Neutral"
        },
        "forecast_7d": [
          26118.13,
          26191.61,
          26265.09,
          26338.56,
          26412.04,
          26485.52,
          26559.0
        ]
      },
      "FMCG": {
        "current": 49310.6,
        "history_30d": [
          49383.35,
          48247.7,
          48612.8,
          48123.95,
          48216.0,
          48302.45,
          48098.65,
          48447.4,
          48957.0,
          48521.8,
          48827.6,
          49043.4,
          49642.4,
          49556.05,
          49654.5,
          49558.7,
          49355.1,
          49059.05,
          49085.1,
          49419.25,
          49127.65,
          48794.2,
          49806.8,
          50084.7,
          50096.4,
          50196.35,
          50225.85,
          48977.4,
          49350.15,
          49310.6
        ],
        "delta_1d": -0.08,
        "delta_1w": -1.57,
        "delta_1m": 0.72,
        "delta_3m": 3.51,
        "delta_6m": -7.1,
        "delta_1y": -13.01,
        "signal": "Buy",
        "rsi": 48.03,
        "macd": {
          "macd": 36.76,
          "signal": 27.22,
          "hist": 9.53
        },
        "pattern": {
          "pattern": "Consolidation",
          "target": 50296.81,
          "stop_loss": 46845.07,
          "strength": "Neutral"
        },
        "forecast_7d": [
          49899.84,
          49949.11,
          49998.39,
          50047.66,
          50096.94,
          50146.21,
          50195.49
        ]
      },
      "Auto": {
        "current": 26860.75,
        "history_30d": [
          26338.45,
          25891.9,
          26079.45,
          26092.8,
          26144.35,
          26165.95,
          25681.8,
          26025.65,
          25833.55,
          25790.35,
          26293.85,
          26977.5,
          26891.55,
          26724.4,
          26746.4,
          26583.35,
          26703.45,
          26496.5,
          26384.35,
          26977.75,
          26417.6,
          26479.8,
          26783.2,
          27108.2,
          26988.1,
          27353.95,
          27343.5,
          26733.4,
          26676.35,
          26860.75
        ],
        "delta_1d": 0.69,
        "delta_1w": -0.47,
        "delta_1m": 3.98,
        "delta_3m": 3.7,
        "delta_6m": -6.75,
        "delta_1y": 11.87,
        "signal": "Buy",
        "rsi": 53.17,
        "macd": {
          "macd": 172.89,
          "signal": 180.05,
          "hist": -7.16
        },
        "pattern": {
          "pattern": "Consolidation",
          "target": 27397.97,
          "stop_loss": 25517.71,
          "strength": "Neutral"
        },
        "forecast_7d": [
          27116.11,
          27154.64,
          27193.16,
          27231.69,
          27270.22,
          27308.74,
          27347.27
        ]
      },
      "Realty": {
        "current": 938.6,
        "history_30d": [
          782.55,
          768.2,
          773.35,
          762.6,
          764.6,
          768.9,
          749.2,
          761.4,
          748.15,
          743.35,
          769.6,
          800.05,
          818.1,
          814.6,
          820.2,
          811.9,
          815.15,
          806.05,
          823.55,
          826.25,
          818.85,
          829.55,
          859.25,
          871.7,
          890.8,
          906.95,
          892.6,
          875.95,
          906.95,
          938.6
        ],
        "delta_1d": 3.49,
        "delta_1w": 5.37,
        "delta_1m": 25.46,
        "delta_3m": 26.2,
        "delta_6m": 4.43,
        "delta_1y": -5.08,
        "signal": "Strong Buy",
        "rsi": 74.4,
        "macd": {
          "macd": 34.07,
          "signal": 25.55,
          "hist": 8.52
        },
        "pattern": {
          "pattern": "Consolidation",
          "target": 957.37,
          "stop_loss": 891.67,
          "strength": "Neutral"
        },
        "forecast_7d": [
          904.12,
          909.72,
          915.32,
          920.93,
          926.53,
          932.13,
          937.73
        ]
      },
      "Energy": {
        "current": 39242.05,
        "history_30d": [
          40878.0,
          40253.65,
          40189.65,
          40196.85,
          40445.75,
          40346.1,
          39685.45,
          39752.95,
          38949.3,
          38655.9,
          39244.45,
          39493.95,
          39915.4,
          40238.45,
          40457.3,
          40548.1,
          40773.8,
          40268.7,
          39908.4,
          39637.0,
          39718.0,
          39740.5,
          39764.85,
          39707.0,
          39178.6,
          39481.45,
          39188.45,
          38695.65,
          38838.1,
          39242.05
        ],
        "delta_1d": 1.04,
        "delta_1w": 0.16,
        "delta_1m": 0.75,
        "delta_3m": 6.73,
        "delta_6m": 8.18,
        "delta_1y": 7.95,
        "signal": "Strong Sell",
        "rsi": 45.16,
        "macd": {
          "macd": -229.34,
          "signal": -124.66,
          "hist": -104.69
        },
        "pattern": {
          "pattern": "Consolidation",
          "target": 40026.89,
          "stop_loss": 37279.95,
          "strength": "Neutral"
        },
        "forecast_7d": [
          39241.08,
          39206.32,
          39171.57,
          39136.81,
          39102.05,
          39067.3,
          39032.54
        ]
      }
    }
  },
  "macroData": {
    "usdInr": {
      "current": 96.33,
      "history_30d": [
        94.95,
        95.69,
        95.36,
        95.64,
        95.76,
        95.11,
        94.74,
        94.89,
        94.86,
        94.34,
        94.33,
        94.7,
        95.18,
        94.44,
        94.4,
        94.36,
        94.79,
        94.92,
        95.42,
        95.53,
        95.21,
        95.6,
        95.59,
        95.86,
        95.39,
        95.32,
        96.3,
        96.43,
        96.5,
        96.33
      ],
      "delta_1d": -0.18,
      "delta_1w": 0.99,
      "delta_1m": 1.55,
      "delta_3m": 2.89,
      "delta_6m": 5.21,
      "delta_1y": 12.16,
      "signal": "Strong Buy",
      "rsi": 60.36,
      "macd": {
        "macd": 0.32,
        "signal": 0.17,
        "hist": 0.15
      },
      "pattern": {
        "pattern": "Consolidation",
        "target": 98.26,
        "stop_loss": 91.51,
        "strength": "Neutral"
      },
      "forecast_7d": [
        95.83,
        95.87,
        95.9,
        95.94,
        95.98,
        96.01,
        96.05
      ]
    },
    "crudeOil": {
      "current": 84.92,
      "history_30d": [
        97.81,
        95.03,
        93.09,
        94.25,
        91.45,
        93.1,
        90.38,
        87.33,
        83.17,
        78.96,
        79.55,
        79.85,
        77.9,
        77.08,
        73.74,
        75.26,
        71.99,
        73.15,
        72.92,
        71.57,
        71.8,
        71.99,
        74.16,
        78.02,
        76.3,
        76.01,
        83.3,
        84.73,
        84.95,
        84.92
      ],
      "delta_1d": -0.04,
      "delta_1w": 11.3,
      "delta_1m": 2.1,
      "delta_3m": -14.56,
      "delta_6m": 27.66,
      "delta_1y": 23.93,
      "signal": "Buy",
      "rsi": 55.94,
      "macd": {
        "macd": -1.59,
        "signal": -3.84,
        "hist": 2.25
      },
      "pattern": {
        "pattern": "Consolidation",
        "target": 86.62,
        "stop_loss": 80.67,
        "strength": "Neutral"
      },
      "forecast_7d": [
        72.7,
        72.14,
        71.57,
        71.01,
        70.44,
        69.88,
        69.31
      ]
    },
    "inflation": {
      "current": 5.1,
      "expectation": "Expected to rise if crude stays >$100."
    }
  },
  "newsData": [
    {
      "title": "Stocks to buy in 2026 for long term: Jindal Saw, SBI Life among 5 stocks that could give 10-20% return ",
      "link": "https://economictimes.indiatimes.com/markets/stocks/news/stocks-to-buy-in-2026-for-long-term-jindal-saw-sbi-life-among-5-stocks-that-could-give-10-20-return/slideshow/132450793.cms",
      "time": "Fri, 17 Jul 2026 07:42:07 +0530",
      "source": "ET Markets"
    },
    {
      "title": "Negative Breakout: These 8 stocks cross below their 200 DMAs ",
      "link": "https://economictimes.indiatimes.com/markets/stocks/news/negative-breakout-these-8-stocks-cross-below-their-200-dmas/slideshow/132450721.cms",
      "time": "Fri, 17 Jul 2026 07:33:09 +0530",
      "source": "ET Markets"
    },
    {
      "title": "Sensex Today | Nifty 50 | Stock Market Live Updates: GIFT Nifty signals a muted start; Asian shares trade lower ",
      "link": "https://economictimes.indiatimes.com/markets/stocks/live-blog/bse-sensex-today-nifty50-stock-market-live-updates-gift-nifty-ril-tata-tech-share-price-17-july-2026/liveblog/132450656.cms",
      "time": "Fri, 17 Jul 2026 07:29:40 +0530",
      "source": "ET Markets"
    },
    {
      "title": "D-St set for a cautious opening as GIFT Nifty signals muted start ",
      "link": "https://economictimes.indiatimes.com/markets/stocks/news/pre-market-action-heres-the-trade-setup-for-todays-session/articleshow/132450414.cms",
      "time": "Fri, 17 Jul 2026 06:41:23 +0530",
      "source": "ET Markets"
    },
    {
      "title": "Stocks in news: Reliance Industries, Tata Tech, Wipro, Jio Financial, ITC, Maruti Suzuki ",
      "link": "https://economictimes.indiatimes.com/markets/stocks/news/stocks-in-news-reliance-industries-tata-tech-wipro-jio-financial-itc-maruti-suzuki/articleshow/132450386.cms",
      "time": "Fri, 17 Jul 2026 06:34:59 +0530",
      "source": "ET Markets"
    },
    {
      "title": "Wipro's strong deal wins offset by weak revenue and margin decline ",
      "link": "https://economictimes.indiatimes.com/markets/stocks/earnings/wipros-strong-deal-wins-offset-by-weak-revenue-and-margin-decline/articleshow/132450336.cms",
      "time": "Fri, 17 Jul 2026 06:27:05 +0530",
      "source": "ET Markets"
    },
    {
      "title": "Logistics firms set for strong Q1 revenue growth despite margin pressure ",
      "link": "https://economictimes.indiatimes.com/markets/stocks/earnings/logistics-firms-set-for-strong-q1-revenue-growth-despite-margin-pressure/articleshow/132450304.cms",
      "time": "Fri, 17 Jul 2026 06:20:11 +0530",
      "source": "ET Markets"
    },
    {
      "title": "Foreign or local? Investors at lossover GIFT funds ",
      "link": "https://economictimes.indiatimes.com/markets/stocks/news/foreign-or-local-investors-at-lossover-gift-funds/articleshow/132450287.cms",
      "time": "Fri, 17 Jul 2026 06:00:00 +0530",
      "source": "ET Markets"
    },
    {
      "title": "Tata, SP Group explore share swap to unlock Tata Sons stake amid valuation divide ",
      "link": "https://economictimes.indiatimes.com/markets/stocks/news/tata-sp-group-explore-share-swap-to-unlock-tata-sons-stake-amid-valuation-divide/articleshow/132450280.cms",
      "time": "Fri, 17 Jul 2026 06:00:00 +0530",
      "source": "ET Markets"
    },
    {
      "title": "HSBC offers 19x FCNR(B) leverage in GIFT City ",
      "link": "https://economictimes.indiatimes.com/markets/stocks/news/hsbc-offers-19x-fcnrb-leverage-in-gift-city/articleshow/132450266.cms",
      "time": "Fri, 17 Jul 2026 05:56:59 +0530",
      "source": "ET Markets"
    },
    {
      "title": "MSCI rejig could bring $2.3 billion into Indian stocks ",
      "link": "https://economictimes.indiatimes.com/markets/stocks/news/msci-rejig-could-bring-2-3-billion-into-indian-stocks/articleshow/132450255.cms",
      "time": "Fri, 17 Jul 2026 05:52:43 +0530",
      "source": "ET Markets"
    },
    {
      "title": "Private insurers seek tweaks in unlisted investment plan ",
      "link": "https://economictimes.indiatimes.com/markets/stocks/news/private-insurers-seek-tweaks-in-unlisted-investment-plan/articleshow/132450147.cms",
      "time": "Fri, 17 Jul 2026 00:49:17 +0530",
      "source": "ET Markets"
    },
    {
      "title": "RBI bars banks, NBFCs from selling acquired stressed assets back to defaulting borrowers, related parties ",
      "link": "https://economictimes.indiatimes.com/markets/stocks/news/rbi-bars-banks-nbfcs-from-selling-acquired-stressed-assets-back-to-defaulting-borrowers-related-parties/articleshow/132450145.cms",
      "time": "Thu, 16 Jul 2026 19:27:58 +0530",
      "source": "ET Markets"
    },
    {
      "title": "Ather Energy's Rs 1,300-crore QIP subscribed over eight times: sources ",
      "link": "https://economictimes.indiatimes.com/markets/stocks/news/athers-rs-1300-crore-qip-subscribed-over-8-times/articleshow/132450247.cms",
      "time": "Thu, 16 Jul 2026 18:02:18 +0530",
      "source": "ET Markets"
    },
    {
      "title": "Blasts reported in Iran as US launches new wave of strikes",
      "link": "https://www.bbc.co.uk/news/articles/c151gdjwd10o?at_medium=RSS&at_campaign=rss",
      "time": "Thu, 16 Jul 2026 23:57:26 GMT",
      "source": "BBC World"
    },
    {
      "title": "Zelensky's removal of popular defence minister sparks protests in Ukraine",
      "link": "https://www.bbc.co.uk/news/articles/cdx76069n3do?at_medium=RSS&at_campaign=rss",
      "time": "Thu, 16 Jul 2026 16:36:21 GMT",
      "source": "BBC World"
    },
    {
      "title": "Teenager accused of carrying out sabotage actions in Poland for Russia",
      "link": "https://www.bbc.co.uk/news/articles/cp305dx493do?at_medium=RSS&at_campaign=rss",
      "time": "Thu, 16 Jul 2026 13:08:28 GMT",
      "source": "BBC World"
    },
    {
      "title": "Fifa 'assessing match reports' over Falklands banner",
      "link": "https://www.bbc.co.uk/sport/football/articles/c75gnkl30vlo?at_medium=RSS&at_campaign=rss",
      "time": "Thu, 16 Jul 2026 18:44:43 GMT",
      "source": "BBC World"
    },
    {
      "title": "Italian officials handed jail terms for Genoa bridge disaster that killed 43",
      "link": "https://www.bbc.co.uk/news/articles/c36dnz1zez5o?at_medium=RSS&at_campaign=rss",
      "time": "Thu, 16 Jul 2026 17:22:31 GMT",
      "source": "BBC World"
    },
    {
      "title": "White House teleprompter operator accused of making $100k off Trump speech bets",
      "link": "https://www.bbc.co.uk/news/articles/cjrvdqyr5d5o?at_medium=RSS&at_campaign=rss",
      "time": "Thu, 16 Jul 2026 18:52:35 GMT",
      "source": "BBC World"
    },
    {
      "title": "Canada fires prompt US air quality alerts as smoke blankets major cities ",
      "link": "https://www.bbc.co.uk/news/articles/c0m7n427xd8o?at_medium=RSS&at_campaign=rss",
      "time": "Fri, 17 Jul 2026 02:15:23 GMT",
      "source": "BBC World"
    },
    {
      "title": "JD Vance accuses Israel of 'manipulating' US public opinion to prolong Iran war",
      "link": "https://www.bbc.co.uk/news/articles/c1m107yj327o?at_medium=RSS&at_campaign=rss",
      "time": "Thu, 16 Jul 2026 21:22:09 GMT",
      "source": "BBC World"
    },
    {
      "title": "Kris Jenner's mother Mary Jo dies aged 91",
      "link": "https://www.bbc.co.uk/news/articles/c70g35n4518o?at_medium=RSS&at_campaign=rss",
      "time": "Thu, 16 Jul 2026 20:24:54 GMT",
      "source": "BBC World"
    },
    {
      "title": "At least one dead in Texas floods ravaging same area where campers died",
      "link": "https://www.bbc.co.uk/news/articles/c3v0xe5elzyo?at_medium=RSS&at_campaign=rss",
      "time": "Thu, 16 Jul 2026 22:08:13 GMT",
      "source": "BBC World"
    },
    {
      "title": "'Moment of joy' as Uganda discharges last Ebola patient",
      "link": "https://www.bbc.co.uk/news/articles/cx2myxjv172o?at_medium=RSS&at_campaign=rss",
      "time": "Thu, 16 Jul 2026 17:15:32 GMT",
      "source": "BBC World"
    },
    {
      "title": "Volunteer firefighter suspected of starting devastating France forest fire",
      "link": "https://www.bbc.co.uk/news/articles/ce97zd8yx1xo?at_medium=RSS&at_campaign=rss",
      "time": "Thu, 16 Jul 2026 12:44:26 GMT",
      "source": "BBC World"
    },
    {
      "title": "Children among dead at Algeria foster care home blaze - president",
      "link": "https://www.bbc.co.uk/news/articles/cvgwd4nz344o?at_medium=RSS&at_campaign=rss",
      "time": "Thu, 16 Jul 2026 16:14:45 GMT",
      "source": "BBC World"
    },
    {
      "title": "New monkey species with orange lips found 'hiding' in DR Congo forest",
      "link": "https://www.bbc.co.uk/news/articles/c15y5wgj4x8o?at_medium=RSS&at_campaign=rss",
      "time": "Wed, 15 Jul 2026 23:02:49 GMT",
      "source": "BBC World"
    },
    {
      "title": "Fraud crackdown on Ghana ID cards makes digital checks compulsory - photocopies banned",
      "link": "https://www.bbc.co.uk/news/articles/cn4n9q538z2o?at_medium=RSS&at_campaign=rss",
      "time": "Thu, 16 Jul 2026 11:18:51 GMT",
      "source": "BBC World"
    },
    {
      "title": "JD Vance says Welsh castle was 'coolest thing I've ever seen'",
      "link": "https://www.bbc.co.uk/news/articles/ckg8g5z83glo?at_medium=RSS&at_campaign=rss",
      "time": "Thu, 16 Jul 2026 16:08:28 GMT",
      "source": "BBC World"
    }
  ]
}